davidkhala/microsoft/purview/__init__.py
davidkhala/microsoft/purview/const.py
davidkhala/microsoft/purview/databricks/__init__.py
davidkhala/microsoft/purview/databricks/lineage.py
davidkhala/microsoft/purview/entity.py
davidkhala/microsoft/purview/fabric/__init__.py
davidkhala/microsoft/purview/fabric/powerbi.py
davidkhala/microsoft/purview/lineage/__init__.py
davidkhala/microsoft/purview/lineage/weaver/__init__.py
davidkhala/microsoft/purview/lineage/weaver/powerbi.py
davidkhala/microsoft/purview/relationship.py
davidkhala/microsoft/purview/scan/__init__.py
davidkhala_microsoft_purview-0.0.0.dist-info/METADATA
davidkhala_microsoft_purview-0.0.0.dist-info/WHEEL
davidkhala_microsoft_purview-0.0.0.dist-info/RECORD
